{"cameraMode":{"drawMode":0,"name":"Shaded","section":"Shading Mode"},"sceneLighting":true,"audioPlay":false,"sceneViewState":{"m_AlwaysRefresh":false,"showFog":true,"showSkybox":true,"showFlares":true,"showImageEffects":true,"showParticleSystems":true,"showVisualEffectGraphs":true,"m_FxEnabled":true},"in2DMode":false,"pivot":{"x":-17.62217140197754,"y":1.7364773750305176,"z":13.920894622802735},"rotation":{"x":-0.15612173080444337,"y":-0.1537301242351532,"z":0.024604491889476777,"w":-0.9754165410995483},"size":10.0,"orthographic":false}